wpydumps/__init__.py
wpydumps/archive.py
wpydumps/model.py
wpydumps/parser.py
wpydumps-0.2.0.dist-info/LICENSE
wpydumps-0.2.0.dist-info/METADATA
wpydumps-0.2.0.dist-info/WHEEL
wpydumps-0.2.0.dist-info/top_level.txt
wpydumps-0.2.0.dist-info/RECORD
