Metadata-Version: 2.1
Name: wpydumps
Version: 0.2.0
Summary: Read Wikipedia dumps
Home-page: https://github.com/bfontaine/wpydumps
Author: Baptiste Fontaine
Author-email: b@ptistefontaine.fr
License: MIT License
Platform: UNKNOWN
Classifier: License :: OSI Approved :: MIT License
Classifier: Programming Language :: Python :: 3.7
Classifier: Programming Language :: Python :: 3.8
Classifier: Programming Language :: Python :: 3.9
Requires-Dist: libarchive
